conexion_gerencia/gerencia_decrypt.py
conexion_gerencia/pkg/__init__.py
conexion_gerencia/pkg/decrypt.py
conexion_gerencia/pkg/get_database.py
conexion_gerencia/pkg/models.py
conexion_gerencia-1.7.2.dist-info/METADATA
conexion_gerencia-1.7.2.dist-info/WHEEL
conexion_gerencia-1.7.2.dist-info/top_level.txt
conexion_gerencia-1.7.2.dist-info/RECORD
