Metadata-Version: 2.2
Name: conexion_gerencia
Version: 1.7.2
Summary: Add your description here
Requires-Python: >=3.9
Requires-Dist: pycryptodome>=3.21.0
Requires-Dist: pydantic>=2.10.5
Requires-Dist: requests>=2.32.3
